lumenspark/__init__.py
lumenspark/lumenspark.py
lumenspark-0.1.5.dist-info/LICENSE
lumenspark-0.1.5.dist-info/METADATA
lumenspark-0.1.5.dist-info/WHEEL
lumenspark-0.1.5.dist-info/top_level.txt
lumenspark-0.1.5.dist-info/RECORD
