Metadata-Version: 2.1
Name: lumenspark
Version: 0.1.5
Summary: Lumenspark: A Transformer Model Optimized for Text Generation and Classification with Low Compute and Memory Requirements.
Home-page: https://github.com/anto18671/lumenspark
Author: Anthony Therrien
License: MIT
Project-URL: Source, https://github.com/anto18671/lumenspark
Project-URL: Documentation, https://github.com/anto18671/lumenspark/blob/main/README.md
Project-URL: Bug Tracker, https://github.com/anto18671/lumenspark/issues
Keywords: transformers,deep learning,NLP,PyTorch,machine learning
Classifier: Development Status :: 3 - Alpha
Classifier: Intended Audience :: Developers
Classifier: Intended Audience :: Science/Research
Classifier: License :: OSI Approved :: MIT License
Classifier: Programming Language :: Python :: 3.8
Classifier: Programming Language :: Python :: 3.9
Classifier: Programming Language :: Python :: 3.10
Classifier: Programming Language :: Python :: 3.11
Classifier: Programming Language :: Python :: 3.12
Classifier: Topic :: Scientific/Engineering :: Artificial Intelligence
Classifier: Operating System :: OS Independent
Requires-Python: >=3.8
License-File: LICENSE
Requires-Dist: torch >=2.0.0
Requires-Dist: transformers >=4.0.0
